evalanche/__init__.py
evalanche/py.typed
evalanche-0.1.1.dist-info/METADATA
evalanche-0.1.1.dist-info/WHEEL
evalanche-0.1.1.dist-info/RECORD
